hintwith/__init__.py
hintwith/__version__.py
hintwith/core.py
hintwith-0.1.5.dist-info/LICENSE
hintwith-0.1.5.dist-info/METADATA
hintwith-0.1.5.dist-info/WHEEL
hintwith-0.1.5.dist-info/top_level.txt
hintwith-0.1.5.dist-info/RECORD
