Metadata-Version: 2.1
Name: hintwith
Version: 0.1.5
Summary: Hints your function with an existing one.
Home-page: https://github.com/Chitaoji/hintwith/
Author: Chitaoji
Author-email: 2360742040@qq.com
License: BSD
Platform: UNKNOWN
Classifier: License :: OSI Approved :: BSD License
Classifier: Programming Language :: Python
Classifier: Programming Language :: Python :: 3
Classifier: Programming Language :: Python :: 3.8
Classifier: Programming Language :: Python :: 3.9
Classifier: Programming Language :: Python :: 3.10
Classifier: Programming Language :: Python :: 3.11
Classifier: Programming Language :: Python :: 3.12
Requires-Python: >=3.8.13
